granavi/__init__.py
granavi/__main__.py
granavi/node.py
granavi/session.py
granavi-0.0.7.dist-info/LICENSE
granavi-0.0.7.dist-info/METADATA
granavi-0.0.7.dist-info/WHEEL
granavi-0.0.7.dist-info/top_level.txt
granavi-0.0.7.dist-info/RECORD
