Metadata-Version: 2.1
Name: granavi
Version: 0.0.7
Summary: Graph navigation
Author-email: Adrian Enns <addis.aden@gmail.com>
Project-URL: Homepage, https://github.com/addisaden/granavi
Project-URL: Bug Tracker, https://github.com/addisaden/granavi/issues
Classifier: Programming Language :: Python :: 3
Classifier: License :: OSI Approved :: MIT License
Classifier: Operating System :: OS Independent
Requires-Python: >=3.7
License-File: LICENSE
